context_cache.py
functions.py
mnotify_mcp/__init__.py
mnotify_mcp/server.py
mnotify_mcp_server-0.1.1.dist-info/METADATA
mnotify_mcp_server-0.1.1.dist-info/WHEEL
mnotify_mcp_server-0.1.1.dist-info/entry_points.txt
mnotify_mcp_server-0.1.1.dist-info/top_level.txt
mnotify_mcp_server-0.1.1.dist-info/RECORD
