Metadata-Version: 2.4
Name: mnotify_mcp_server
Version: 0.1.1
Summary: MNotify MCP server: expose MNotify SMS tools over the Model Context Protocol
Requires-Python: >=3.10
Requires-Dist: mcp[cli]>=1.1.1
Requires-Dist: fastmcp>=2.11.3
Requires-Dist: python-dotenv>=1.1.1
Requires-Dist: requests>=2.32.4
Requires-Dist: httpx>=0.28.1
Requires-Dist: openai>=1.100.2
